ml_dataset_tools/__init__.py
ml_dataset_tools/file_list.py
ml_dataset_tools/sync_file_lists.py
ml_dataset_tools/version.py
ml_dataset_tools-0.1.1.dist-info/LICENSE
ml_dataset_tools-0.1.1.dist-info/METADATA
ml_dataset_tools-0.1.1.dist-info/WHEEL
ml_dataset_tools-0.1.1.dist-info/entry_points.txt
ml_dataset_tools-0.1.1.dist-info/top_level.txt
ml_dataset_tools-0.1.1.dist-info/RECORD
