Metadata-Version: 2.1
Name: ml-dataset-tools
Version: 0.1.1
Summary: Tools for data set handling. Primarily for deep learning and computer vision tasks.
Home-page: https://github.com/serge-m/ml-dataset-tools
Author: SergeM
Author-email: serge-m@users.noreply.github.com
License: MIT license
Keywords: ml_dataset_tools
Platform: UNKNOWN
Classifier: Development Status :: 2 - Pre-Alpha
Classifier: Intended Audience :: Developers
Classifier: License :: OSI Approved :: MIT License
Classifier: Natural Language :: English
Classifier: Programming Language :: Python :: 3
Classifier: Programming Language :: Python :: 3.5
Classifier: Programming Language :: Python :: 3.6
Classifier: Programming Language :: Python :: 3.7
Classifier: Programming Language :: Python :: 3.8
Requires-Python: >=3.5
Requires-Dist: numpy
Requires-Dist: dataclasses ; python_version < "3.7"
